aioratelimits.py
aioratelimits-0.2.6.dist-info/WHEEL
aioratelimits-0.2.6.dist-info/METADATA
aioratelimits-0.2.6.dist-info/RECORD
