Metadata-Version: 2.1
Name: aioratelimits
Version: 0.2.6
Summary: 
Home-page: https://github.com/kupec/aioratelimits
Keywords: rates,ratelimit,ratelimiter,leaky,bucket
Author: Dmitry Kostromin
Author-email: kupec-k@ya.ru
Requires-Python: >=3.7,<4.0
Classifier: Programming Language :: Python :: 3
Classifier: Programming Language :: Python :: 3.10
Classifier: Programming Language :: Python :: 3.7
Classifier: Programming Language :: Python :: 3.8
Classifier: Programming Language :: Python :: 3.9
Project-URL: Repository, https://github.com/kupec/aioratelimits
